CheeseSignal/__init__.py
CheeseSignal/signal.py
cheesesignal-2.1.1.dist-info/METADATA
cheesesignal-2.1.1.dist-info/WHEEL
cheesesignal-2.1.1.dist-info/licenses/LICENSE
cheesesignal-2.1.1.dist-info/RECORD
