Metadata-Version: 2.4
Name: CheeseSignal
Version: 2.1.1
Summary: 一款简约的信号系统。
Project-URL: Source, https://github.com/CheeseUnknown/CheeseSignal
Author-email: Cheese Unknown <cheese@cheese.ren>
License-File: LICENSE
Keywords: Signal
